ugraph/__init__.py
ugraph/_abc/__init__.py
ugraph/_abc/_debug.py
ugraph/_abc/_immutablenetwork.py
ugraph/_abc/_link.py
ugraph/_abc/_mutablenetwork.py
ugraph/_abc/_node.py
ugraph/plot/__init__.py
ugraph/plot/_options.py
ugraph/plot/compose_sequence.py
ugraph/plot/plot_2d.py
ugraph/plot/plot_3d.py
ugraph-0.80.0.dist-info/LICENSE
ugraph-0.80.0.dist-info/METADATA
ugraph-0.80.0.dist-info/WHEEL
ugraph-0.80.0.dist-info/RECORD
