Metadata-Version: 2.3
Name: ugraph
Version: 0.80.0
Summary: 
License: MIT
Keywords: graphs,igraph,typed-graphs,visualization
Author: flfuchs tdubach
Author-email: flfuchs@student.ethz.ch
Requires-Python: >=3.10,<4.0
Classifier: License :: OSI Approved :: MIT License
Classifier: Programming Language :: Python :: 3
Classifier: Programming Language :: Python :: 3.10
Classifier: Programming Language :: Python :: 3.11
Classifier: Programming Language :: Python :: 3.12
Classifier: Programming Language :: Python :: 3.13
Provides-Extra: cairo
Provides-Extra: plotting
Requires-Dist: igraph (>=0.11.8,<0.12.0)
Requires-Dist: plotly (>=5.24.1,<6.0.0) ; extra == "plotting"
Requires-Dist: pycairo (>=1.27.0,<2.0.0) ; extra == "cairo"
Project-URL: Documentation, https://github.com/WonJayne/ugraph/blob/main/docs/getting_started.md
Project-URL: Homepage, https://github.com/WonJayne/ugraph
Project-URL: Repository, https://github.com/WonJayne/ugraph
